setup.cfg
setup.py
mr_csv_worker/__init__.py
mr_csv_worker/error_tracer.py
mr_csv_worker/worker.py
mr_csv_worker.egg-info/PKG-INFO
mr_csv_worker.egg-info/SOURCES.txt
mr_csv_worker.egg-info/dependency_links.txt
mr_csv_worker.egg-info/top_level.txt