Metadata-Version: 1.1
Name: mr-csv-worker
Version: 0.0.1
Summary: Small package for assist telegram bot development
Home-page: https://github.com/r00tkid/mr_csv_worker.git
Author: Root Kid
Author-email: shaman@born2fish.ru
License: UNKNOWN
Download-URL: https://github.com/r00tkid/mr_csv_worker/tarball/0.0.1
Keywords: support,csv,read csv,write csv
Platform: UNKNOWN
